medical_named_entity_recognition/__init__.py
medical_named_entity_recognition/disease_finder.py
medical_named_entity_recognition/disease_ner_dictionary.pkl.bz2
medical_named_entity_recognition/util.py
medical_named_entity_recognition-0.2.dist-info/LICENSE
medical_named_entity_recognition-0.2.dist-info/METADATA
medical_named_entity_recognition-0.2.dist-info/WHEEL
medical_named_entity_recognition-0.2.dist-info/top_level.txt
medical_named_entity_recognition-0.2.dist-info/RECORD
