Metadata-Version: 2.1
Name: medical-named-entity-recognition
Version: 0.2
Summary: Medical Named Entity Recognition library to find and resolve disease names in a string (disease named entity linking)
Home-page: https://fastdatascience.com/drug-named-entity-recognition-python-library
Author: Thomas Wood
Author-email: Thomas Wood <thomas@fastdatascience.com>
Maintainer-email: Thomas Wood <thomas@fastdatascience.com>
License: MIT License
Project-URL: Documentation, https://fastdatascience.com/drug-named-entity-recognition-python-library/
Project-URL: Bug Reports, https://github.com/fastdatascience/medical_named_entity_recognition/issues
Project-URL: Source Code, https://github.com/fastdatascience/medical_named_entity_recognition
Keywords: medicine,bio,biomedical,medical,pharma,pharmaceutical,ner,nlp,named entity recognition,natural language processing,named entity linking,clinical,ehr,electronic health record
Classifier: Development Status :: 5 - Production/Stable
Classifier: Intended Audience :: Developers
Classifier: Topic :: Software Development :: Build Tools
Classifier: Programming Language :: Python :: 3
Classifier: Programming Language :: Python :: 3.6
Classifier: Programming Language :: Python :: 3.7
Classifier: Programming Language :: Python :: 3.8
Classifier: Programming Language :: Python :: 3.9
Classifier: Programming Language :: Python :: 3.10
Classifier: Programming Language :: Python :: 3.11
Classifier: Programming Language :: Python :: 3.12
Classifier: Programming Language :: Python :: 3.13
Classifier: Programming Language :: Python :: 3 :: Only
Classifier: License :: OSI Approved :: MIT License
Classifier: Operating System :: OS Independent
Requires-Python: >=3.6
License-File: LICENSE
Requires-Dist: requests
Provides-Extra: dev
Requires-Dist: check-manifest; extra == "dev"
Requires-Dist: pytest; extra == "dev"
Requires-Dist: nltk; extra == "dev"
Requires-Dist: pandas; extra == "dev"
